<Ui xmlns="http://www.blizzard.com/wow/ui/">
	<!-- AFK -->
	<Script file="AFK\Core.lua"/>
	<!-- Panels -->
	<Script file="Panels\Core.lua"/>
	<!-- ActionBars -->
	<Script file="ActionBars\Core.lua"/>
	<Script file="ActionBars\Skin.lua"/>
	<Script file="ActionBars\Bar1.lua"/>
	<Script file="ActionBars\Bar2.lua"/>
	<Script file="ActionBars\Bar3.lua"/>
	<Script file="ActionBars\Bar4.lua"/>
	<Script file="ActionBars\Bar5.lua"/>
	<Script file="ActionBars\PetBar.lua"/>
	<Script file="ActionBars\StanceBar.lua"/>
	<Script file="ActionBars\Extra.lua"/>
	<Script file="ActionBars\Vehicle.lua"/>
	<Script file="ActionBars\ToggleButtons.lua"/>
	<Script file="ActionBars\Range.lua"/>
	<Script file="ActionBars\Glow.lua"/>
	<!-- Auras -->
	<Script file="Auras\Core.lua"/>
	<!-- Chat -->
	<Script file="Chat\Core.lua"/>
	<Script file="Chat\CopyChat.lua"/>
	<Script file="Chat\CopyURL.lua"/>
	<Script file="Chat\CombatLog.lua"/>
	<!-- CooldownFrame -->
	<Script file="CooldownFrame\Core.lua"/>
	<!-- CooldownManager -->
	<Script file="CooldownManager\Core.lua"/>
	<Script file="CooldownManager\Icons.lua"/>
	<Script file="CooldownManager\Layout.lua"/>
	<!-- DataBars -->
	<Script file="DataBars\ClassPowerBar.lua"/>
	<Script file="DataBars\ExperienceBar.lua"/>
	<Script file="DataBars\PowerBar.lua"/>
	<Script file="DataBars\RuneBar.lua"/>
	<Script file="DataBars\StaggerBar.lua"/>
	<Script file="DataBars\SoulFragmentsBar.lua"/>
	<Script file="DataBars\MaelstormBar.lua"/>
	<Script file="DataBars\TotemBar.lua"/>
	<!-- DataTexts -->
	<Script file="DataTexts\Date.lua"/>
	<Script file="DataTexts\Durability.lua"/>
	<Script file="DataTexts\Memory.lua"/>
	<Script file="DataTexts\System.lua"/>
	<Script file="DataTexts\Time.lua"/>
	<!-- Bags -->
	<Script file="Bags\Core.lua"/>	
	<!-- Loot -->
	<Script file="Loot\Core.lua"/>
	<!-- Maps -->
	<Script file="Maps\Core.lua"/>
	<Script file="Maps\MinimapButtonsBar.lua"/>
	<!-- Misc -->
	<Script file="Misc\Blizzard.lua"/>
	<Script file="Misc\ErrorFilter.lua"/>
	<Script file="Misc\LossControl.lua"/>
	<Script file="Misc\Merchant.lua"/>
	<Script file="Misc\MirrorTimers.lua"/>
	<Script file="Misc\ObjectiveTracker.lua"/>
	<Script file="Misc\TimeTrackers.lua"/>
	<!-- Skins Blizzard -->
	<Script file="Skins\Blizzard\Bubbles.lua"/>
	<Script file="Skins\Blizzard\GameMenu.lua"/>
	<Script file="Skins\Blizzard\GhostFrame.lua"/>
	<Script file="Skins\Blizzard\StackSplitFrame.lua"/>
	<Script file="Skins\Blizzard\TalkingHead.lua"/>
	<Script file="Skins\Blizzard\DeathRecap.lua"/>
	<Script file="Skins\Blizzard\DamageMeter.lua"/>
	<!-- Tooltip -->
	<Script file="Tooltip\Core.lua"/>
	<!-- NamePlates -->
	<Script file="Nameplates\Core.lua"/>
	<Script file="Nameplates\Spawn.lua"/>
	<Script file="Nameplates\Elements\Auras.lua"/>
	<Script file="Nameplates\Elements\Castbar.lua"/>
	<Script file="Nameplates\Elements\Health.lua"/>
	<Script file="Nameplates\Elements\Highlight.lua"/>
	<Script file="Nameplates\Elements\Icons.lua"/>
	<Script file="Nameplates\Elements\Texts.lua"/>
	<Script file="Nameplates\Elements\Threat.lua"/>
	<Script file="Nameplates\Elements\UnitColors.lua"/>
	<!-- UnitFrames -->
	<Script file="UnitFrames\Core.lua"/>
	<Script file="UnitFrames\Groups.lua"/>
	<Script file="UnitFrames\Spawn.lua"/>
	<Script file="UnitFrames\Elements\AdditionalPower.lua"/>
	<Script file="UnitFrames\Elements\Auras.lua"/>
	<Script file="UnitFrames\Elements\Castbar.lua"/>
	<Script file="UnitFrames\Elements\DebuffHighlight.lua"/>
	<Script file="UnitFrames\Elements\Health.lua"/>
	<Script file="UnitFrames\Elements\HealthPred.lua"/>
	<Script file="UnitFrames\Elements\Highlight.lua"/>
	<Script file="UnitFrames\Elements\Icons.lua"/>
	<Script file="UnitFrames\Elements\Portraits.lua"/>
	<Script file="UnitFrames\Elements\Texts.lua"/>
	<Script file="UnitFrames\Elements\Threat.lua"/>
</Ui>